setup.py
best_feature/BestSubsetSelection.py
best_feature/ForwardStepwiseSelection.py
best_feature/__init__.py
best_feature.egg-info/PKG-INFO
best_feature.egg-info/SOURCES.txt
best_feature.egg-info/dependency_links.txt
best_feature.egg-info/not-zip-safe
best_feature.egg-info/top_level.txt